fpr_packer/__init__.py
fpr_packer/plugin.py
fpr_packer/pyinfra.py
fpr_packer/scripts.py
fpr_packer/aws/__init__.py
fpr_packer/aws/aws.py
fpr_packer-0.2.3.dist-info/DESCRIPTION.rst
fpr_packer-0.2.3.dist-info/METADATA
fpr_packer-0.2.3.dist-info/RECORD
fpr_packer-0.2.3.dist-info/WHEEL
fpr_packer-0.2.3.dist-info/entry_points.txt
fpr_packer-0.2.3.dist-info/metadata.json
fpr_packer-0.2.3.dist-info/top_level.txt
