Metadata-Version: 2.0
Name: fpr-packer
Version: 0.2.3
Summary: Python utilities for packer deploiments
Home-page: UNKNOWN
Author: Guillaume Doumenc
Author-email: gdoumenc@fpr-coworks.com
License: UNKNOWN
Platform: UNKNOWN
Classifier: Development Status :: 3 - Alpha
Classifier: Programming Language :: Python :: 3.6
Classifier: Framework :: Pytest
Requires-Python: >=3.6
